openImageDatasetSDKTest-1.0.3.dist-info/DESCRIPTION.rst
openImageDatasetSDKTest-1.0.3.dist-info/METADATA
openImageDatasetSDKTest-1.0.3.dist-info/RECORD
openImageDatasetSDKTest-1.0.3.dist-info/WHEEL
openImageDatasetSDKTest-1.0.3.dist-info/metadata.json
openImageDatasetSDKTest-1.0.3.dist-info/top_level.txt
openimagedataset/__init__.py
openimagedataset/_open_image.py
openimagedataset/environ.py
openimagedataset/_utils/__init__.py
openimagedataset/_utils/image_annotation_table_loader.py
openimagedataset/_utils/image_common_types.py
openimagedataset/_utils/image_downloader.py
openimagedataset/_utils/image_selector.py
openimagedataset/_utils/telemetry_utils.py
openimagedataset/dataaccess/__init__.py
openimagedataset/dataaccess/_open_image_blob_info.py
